signrequest_client/__init__.py
signrequest_client/api_client.py
signrequest_client/configuration.py
signrequest_client/rest.py
signrequest_client/api/__init__.py
signrequest_client/api/api_tokens_api.py
signrequest_client/api/document_attachments_api.py
signrequest_client/api/documents_api.py
signrequest_client/api/documents_search_api.py
signrequest_client/api/events_api.py
signrequest_client/api/signrequest_quick_create_api.py
signrequest_client/api/signrequests_api.py
signrequest_client/api/team_members_api.py
signrequest_client/api/teams_api.py
signrequest_client/api/templates_api.py
signrequest_client/api/webhooks_api.py
signrequest_client/models/__init__.py
signrequest_client/models/auth_token.py
signrequest_client/models/document.py
signrequest_client/models/document_attachment.py
signrequest_client/models/document_search.py
signrequest_client/models/document_signer_template_conf.py
signrequest_client/models/document_signing_log.py
signrequest_client/models/document_signrequest.py
signrequest_client/models/document_team.py
signrequest_client/models/event.py
signrequest_client/models/file_from_sf.py
signrequest_client/models/inline_document_signer_integration_data.py
signrequest_client/models/inline_integration_data.py
signrequest_client/models/inline_prefill_tags.py
signrequest_client/models/inline_response200.py
signrequest_client/models/inline_response2001.py
signrequest_client/models/inline_response2002.py
signrequest_client/models/inline_response2003.py
signrequest_client/models/inline_response2004.py
signrequest_client/models/inline_response2005.py
signrequest_client/models/inline_response2006.py
signrequest_client/models/inline_response2007.py
signrequest_client/models/inline_response2008.py
signrequest_client/models/inline_response2009.py
signrequest_client/models/inline_response201.py
signrequest_client/models/inline_response2011.py
signrequest_client/models/inline_response_200.py
signrequest_client/models/inline_response_200_1.py
signrequest_python_client-2.1.0.dist-info/LICENCE
signrequest_python_client-2.1.0.dist-info/METADATA
signrequest_python_client-2.1.0.dist-info/WHEEL
signrequest_python_client-2.1.0.dist-info/top_level.txt
signrequest_python_client-2.1.0.dist-info/RECORD
