Metadata-Version: 2.1
Name: signrequest-python-client
Version: 2.1.0
Summary: SignRequest API
Home-page: https://github.com/SignRequest/signrequest-python-client/
Author-email: tech-support@signrequest.com
License: UNKNOWN
Keywords: SignRequest,SignRequest API
Platform: UNKNOWN
Requires-Dist: certifi (>=2017.4.17)
Requires-Dist: python-dateutil (>=2.1)
Requires-Dist: six (>=1.10)
Requires-Dist: urllib3 (>=1.23)
